LICENSE
MANIFEST.in
README.md
VERSION
requirements.txt
setup.cfg
setup.py
AgglomCluster.egg-info/PKG-INFO
AgglomCluster.egg-info/SOURCES.txt
AgglomCluster.egg-info/dependency_links.txt
AgglomCluster.egg-info/not-zip-safe
AgglomCluster.egg-info/requires.txt
AgglomCluster.egg-info/top_level.txt
hac/__init__.py
hac/cluster.c
hac/cluster.cpython-36m-x86_64-linux-gnu.so
hac/cluster.pyx
hac/cluster.so
hac/renamemap.py