Metadata-Version: 1.1
Name: AgglomCluster
Version: 2.0.7
Summary: Performs greedy agglomerative clustering on network-x graphs
Home-page: https://github.com/MSeal/agglom_cluster
Author: Matthew Seal
Author-email: mseal@opengov.com
License: LGPL 2.1
Download-URL: https://github.com/MSeal/agglom_cluster/tarball/v2.0.7
Keywords: network-x,data,graphs,clustering,agglomerative
Platform: UNKNOWN
Classifier: Development Status :: 4 - Beta
Classifier: Topic :: Utilities
Classifier: License :: OSI Approved :: GNU Lesser General Public License v2 (LGPLv2)
Classifier: Natural Language :: English
Classifier: Programming Language :: Python :: 2.7
Classifier: Programming Language :: Python :: 3
